leezy/__init__.py
leezy/__main__.py
leezy/assists.py
leezy/config.py
leezy/config_test.py
leezy/core.py
leezy/crawler.py
leezy/errors.py
leezy/plot.py
leezy/render.py
leezy/templite.py
leezy/templite_test.py
leezy/utils.py
leezy-0.5.3.dist-info/METADATA
leezy-0.5.3.dist-info/WHEEL
leezy-0.5.3.dist-info/entry_points.txt
leezy-0.5.3.dist-info/top_level.txt
leezy-0.5.3.dist-info/RECORD
