Metadata-Version: 2.1
Name: leezy
Version: 0.5.3
Summary: leezy: leetcode helper for the lazy
Home-page: https://github.com/aptend/leezy
Author: aptend
Author-email: aptend@hotmail.com
License: MIT
Platform: UNKNOWN
Classifier: Operating System :: OS Independent
Classifier: Programming Language :: Python :: 3.6
Classifier: Programming Language :: Python :: 3.7
Classifier: Programming Language :: Python :: 3.8
Classifier: Programming Language :: Python :: 3.9
Classifier: Topic :: Text Processing
Classifier: Topic :: Utilities
Requires-Python: >=3.6
Requires-Dist: requests (>=2.18.0)
Requires-Dist: pytest (>=5.1.3)
